djangorestframework_orjson-0.1.3.dist-info/RECORD
djangorestframework_orjson-0.1.3.dist-info/metadata.json
djangorestframework_orjson-0.1.3.dist-info/WHEEL
djangorestframework_orjson-0.1.3.dist-info/DESCRIPTION.rst
djangorestframework_orjson-0.1.3.dist-info/top_level.txt
djangorestframework_orjson-0.1.3.dist-info/METADATA
rest_framework_orjson/__init__.py
rest_framework_orjson/parsers.py
rest_framework_orjson/renderers.py
rest_framework_orjson/__pycache__/renderers.cpython-37.pyc
rest_framework_orjson/__pycache__/parsers.cpython-37.pyc
rest_framework_orjson/__pycache__/__init__.cpython-37.pyc
