Metadata-Version: 2.0
Name: djangorestframework-orjson
Version: 0.1.3
Summary: Provides parser and renderer support for orjson library
Home-page: https://github.com/mauricioabreu/django-rest-framework-orjson
Author: Maurício de Abreu Antunes
Author-email: mauricio.abreua@gmail.com
License: BSD
Platform: UNKNOWN
Classifier: Development Status :: 2 - Pre-Alpha
Classifier: Environment :: Web Environment
Classifier: Framework :: Django
Classifier: Intended Audience :: Developers
Classifier: License :: OSI Approved :: BSD License
Classifier: Operating System :: OS Independent
Classifier: Natural Language :: English
Classifier: Programming Language :: Python :: 3
Classifier: Programming Language :: Python :: 3.5
Classifier: Programming Language :: Python :: 3.6
Classifier: Programming Language :: Python :: 3.7
Classifier: Topic :: Internet :: WWW/HTTP
Requires-Python: >=3.5.*
Requires-Dist: Django (>=1.11)
Requires-Dist: djangorestframework (>=3.6.3)
Requires-Dist: orjson (>=2.0.5)
